figurestophoto.py
figurestophoto-1.0.4.dist-info/WHEEL
figurestophoto-1.0.4.dist-info/METADATA
figurestophoto-1.0.4.dist-info/RECORD
