Metadata-Version: 2.1
Name: figurestophoto
Version: 1.0.4
Summary: EN: This module is needed to quickly draw shapes! First, install Pillow! RU: Этот модуль нужен, чтобы быстро рисовать фигуры! Для начала установите Pillow!
Author: RealGames70
Author-email: 69468716+RealGames70@users.noreply.github.com
Requires-Python: >=3.4,<4.0
Classifier: Programming Language :: Python :: 3
Classifier: Programming Language :: Python :: 3.4
Classifier: Programming Language :: Python :: 3.5
Classifier: Programming Language :: Python :: 3.6
Classifier: Programming Language :: Python :: 3.7
Classifier: Programming Language :: Python :: 3.8
